Metadata-Version: 2.1
Name: hpecloudvolumes
Version: 1.0.0
Summary: HPE CloudVolumes Python Library
Home-page: https://cloudvolumes.hpe.com
Author: HPE CloudVolumes
License: MIT
Project-URL: Source, https://github.com/nimblestorage/hpecloudvolumes
Keywords: cloud volumes storage nimble hpe
Platform: UNKNOWN
Classifier: Development Status :: 4 - Beta
Classifier: Intended Audience :: Developers
Classifier: Intended Audience :: Information Technology
Classifier: Intended Audience :: Science/Research
Classifier: Intended Audience :: System Administrators
Classifier: License :: OSI Approved :: MIT License
Classifier: Natural Language :: English
Classifier: Operating System :: Microsoft :: Windows
Classifier: Operating System :: POSIX :: Linux
Classifier: Operating System :: MacOS
Classifier: Programming Language :: Python :: 3
Classifier: Programming Language :: Python :: 3 :: Only
Classifier: Topic :: Software Development :: Libraries
Classifier: Topic :: Utilities
Requires-Python: >=3.6
